aliyunsdkesa/__init__.py
aliyunsdkesa/request/__init__.py
aliyunsdkesa/request/v20240910/ActivateClientCertificateRequest.py
aliyunsdkesa/request/v20240910/AddUserBusinessFormRequest.py
aliyunsdkesa/request/v20240910/AdvancePurgeObjectCacheRequest.py
aliyunsdkesa/request/v20240910/BatchCreateRecordsRequest.py
aliyunsdkesa/request/v20240910/BatchCreateWafRulesRequest.py
aliyunsdkesa/request/v20240910/BatchDeleteKvRequest.py
aliyunsdkesa/request/v20240910/BatchDeleteKvWithHighCapacityRequest.py
aliyunsdkesa/request/v20240910/BatchGetExpressionFieldsRequest.py
aliyunsdkesa/request/v20240910/BatchPutKvRequest.py
aliyunsdkesa/request/v20240910/BatchPutKvWithHighCapacityRequest.py
aliyunsdkesa/request/v20240910/BatchUpdateWafRulesRequest.py
aliyunsdkesa/request/v20240910/BlockObjectRequest.py
aliyunsdkesa/request/v20240910/ChangeResourceGroupRequest.py
aliyunsdkesa/request/v20240910/CheckSiteNameRequest.py
aliyunsdkesa/request/v20240910/CheckSiteProjectNameRequest.py
aliyunsdkesa/request/v20240910/CheckUserProjectNameRequest.py
aliyunsdkesa/request/v20240910/CreateCustomScenePolicyRequest.py
aliyunsdkesa/request/v20240910/CreateKvNamespaceRequest.py
aliyunsdkesa/request/v20240910/CreateListRequest.py
aliyunsdkesa/request/v20240910/CreateManagedRulesGroupRequest.py
aliyunsdkesa/request/v20240910/CreatePageRequest.py
aliyunsdkesa/request/v20240910/CreateRecordRequest.py
aliyunsdkesa/request/v20240910/CreateScheduledPreloadExecutionsRequest.py
aliyunsdkesa/request/v20240910/CreateScheduledPreloadJobRequest.py
aliyunsdkesa/request/v20240910/CreateSiteCustomLogRequest.py
aliyunsdkesa/request/v20240910/CreateSiteDeliveryTaskRequest.py
aliyunsdkesa/request/v20240910/CreateSiteRequest.py
aliyunsdkesa/request/v20240910/CreateUserDeliveryTaskRequest.py
aliyunsdkesa/request/v20240910/CreateWafRuleRequest.py
aliyunsdkesa/request/v20240910/CreateWaitingRoomEventRequest.py
aliyunsdkesa/request/v20240910/CreateWaitingRoomRequest.py
aliyun_python_sdk_esa-1.0.0.dist-info/LICENSE
aliyun_python_sdk_esa-1.0.0.dist-info/METADATA
aliyun_python_sdk_esa-1.0.0.dist-info/WHEEL
aliyun_python_sdk_esa-1.0.0.dist-info/top_level.txt
aliyun_python_sdk_esa-1.0.0.dist-info/RECORD
